snovio/__init__.py
python_snovio-0.1.5.dist-info/LICENSE.txt
python_snovio-0.1.5.dist-info/METADATA
python_snovio-0.1.5.dist-info/WHEEL
python_snovio-0.1.5.dist-info/top_level.txt
python_snovio-0.1.5.dist-info/RECORD
