Metadata-Version: 2.1
Name: python-snovio
Version: 0.1.5
Summary: A Python wrapper around Snov.io API
Home-page: http://github.com/miguelcdpmarques/python-snovio
Author: Miguel Marques
Author-email: miguelcdpmarques@gmail.com
License: MIT
Download-URL: https://github.com/miguelcdpmarques/python-snovio/archive/0.1.0.tar.gz
Platform: UNKNOWN
Classifier: Development Status :: 3 - Alpha
Classifier: Environment :: Web Environment
Classifier: Intended Audience :: Developers
Classifier: Operating System :: OS Independent
Classifier: Programming Language :: Python
Requires-Dist: requests
